coubeh/__init__.py
quoi/__init__.py
coubeh-3.0.dist-info/LICENSE
coubeh-3.0.dist-info/METADATA
coubeh-3.0.dist-info/WHEEL
coubeh-3.0.dist-info/top_level.txt
coubeh-3.0.dist-info/RECORD
